cfn_lint_ax/__init__.py
cfn_lint_ax/_utils.py
cfn_lint_ax/rules/__init__.py
cfn_lint_ax/rules/certificate_manager.py
cfn_lint_ax/rules/cloud_front.py
cfn_lint_ax/rules/code_build.py
cfn_lint_ax/rules/ecr.py
cfn_lint_ax/rules/ecs.py
cfn_lint_ax/rules/intrinsic_function.py
cfn_lint_ax/rules/metadata.py
cfn_lint_ax/rules/s3.py
cfn_lint_ax/rules/sqs.py
cfn_lint_ax/rules/tags.py
cfn_lint_ax/serverless_rules/__init__.py
cfn_lint_ax/serverless_rules/api_gateway.py
cfn_lint_ax/serverless_rules/appsync.py
cfn_lint_ax/serverless_rules/eventbridge.py
cfn_lint_ax/serverless_rules/lambda_.py
cfn_lint_ax/serverless_rules/sns.py
cfn_lint_ax/serverless_rules/sqs.py
cfn_lint_ax/serverless_rules/step_functions.py
cfn_lint_ax-1.3.0.dist-info/licenses/LICENSE
cfn_lint_ax-1.3.0.dist-info/METADATA
cfn_lint_ax-1.3.0.dist-info/WHEEL
cfn_lint_ax-1.3.0.dist-info/top_level.txt
cfn_lint_ax-1.3.0.dist-info/RECORD
