Metadata-Version: 2.4
Name: cfn_lint_ax
Version: 1.3.0
Summary: Rules for cfn lint.
Author-email: AX Semantics <infrastructure@ax-semantics.com>
License-Expression: MIT
Project-URL: Source, https://github.com/aexeagmbh/cfn-lint-rules
Project-URL: Tracker, https://github.com/aexeagmbh/cfn-lint-rules/issues
Keywords: cloudformation,lint,cfn-lint
Classifier: Development Status :: 5 - Production/Stable
Classifier: Intended Audience :: Developers
Classifier: Operating System :: OS Independent
Classifier: Programming Language :: Python :: 3
Classifier: Programming Language :: Python :: 3 :: Only
Classifier: Programming Language :: Python :: 3.10
Classifier: Programming Language :: Python :: 3.11
Classifier: Programming Language :: Python :: 3.12
Classifier: Programming Language :: Python :: 3.13
Requires-Python: >=3.10
License-File: LICENSE
Requires-Dist: cfn-lint>=1.18.1
Dynamic: license-file
